megaparse_sdk/__init__.py
megaparse_sdk/client.py
megaparse_sdk/config.py
megaparse_sdk/endpoints/__init__.py
megaparse_sdk/endpoints/file_upload.py
megaparse_sdk/endpoints/url_upload.py
megaparse_sdk/schema/__init__.py
megaparse_sdk/schema/extensions.py
megaparse_sdk/schema/languages.py
megaparse_sdk/schema/mp_exceptions.py
megaparse_sdk/schema/mp_inputs.py
megaparse_sdk/schema/mp_outputs.py
megaparse_sdk/schema/parser_config.py
megaparse_sdk/schema/supported_models.py
megaparse_sdk/utils/load_ssl.py
megaparse_sdk-0.1.10.dist-info/METADATA
megaparse_sdk-0.1.10.dist-info/WHEEL
megaparse_sdk-0.1.10.dist-info/RECORD
