Metadata-Version: 2.3
Name: megaparse-sdk
Version: 0.1.10
Summary: Megaparse SDK
Requires-Python: <3.12
Requires-Dist: httpx>=0.27.0
Requires-Dist: loguru>=0.7.2
Requires-Dist: nats-py>=2.9.0
Requires-Dist: psutil>=6.1.0
Requires-Dist: pycryptodome>=3.21.0
Requires-Dist: python-dotenv>=1.0.0
